pybuild-0.0.1.dist-info/METADATA
pybuild-0.0.1.dist-info/WHEEL
pybuild/__init__.py
pybuild/pybuild.abi3.so
pybuild-0.0.1.dist-info/RECORD
