Metadata-Version: 2.1
Name: pybuild
Version: 0.0.1
Classifier: Programming Language :: Rust
Classifier: Programming Language :: Python :: Implementation :: CPython
Classifier: Programming Language :: Python :: Implementation :: PyPy
Summary: Python src+dependency bundler.
Keywords: bundler
Home-Page: https://github.com/serverless-delivery/pybuild
Author: Bryant Biggs <bryantbiggs@gmail.com>
Author-email: Bryant Biggs <bryantbiggs@gmail.com>
License:                                  Apache License
Requires-Python: >=3.7
Project-URL: Source Code, https://github.com/serverless-delivery/pybuild/pybuild-py
